{
  "currentLanguage": "EN",
  "weather": "Today's Weather",
  "clear": "Clear",
  "noAvatar": "You have not created avatar yet!",
  "variousOutfitsAvatar": "Easily try on various outfits by creating your avatar.",
  "recommendedStyle": "Recommended Style",
  "wardrobeRecommend": "We recommend a combination of a light dress, blouses, and skirt.",
  "recommendedBrands": "Recommended Brands",
  "myWardrobe": "My Wardrobe",
  "shopNow": "Shop Now",
  "fashionFeed": "Fashion Feed",
  "variousStyles": "Explore various styles in real time!",
  "categoriesDescription": "Categories or Description",
  "popularItems": "Popular Items",
  "virtualFitting": "Start Virtual Fitting",
  "newCollection": "Winter New Collection",
  "brandNaming": "Brand Naming",
  "productNaming": "Product Naming",
  "moreProducts": "View More Products",
  "personalizedAvatar": "My Personalized Style Avatar",
  "lightCasual": "Light Casual"
}
